Changelog.md
LICENSE.txt
README.md
setup.py
ds1052/__init__.py
ds1052/exceptions.py
ds1052/tmc.py
ds1052/examples/__init__.py
ds1052/examples/plot.py
ds1052/examples/plot_ch1.py
ds1052/examples/save_load_config.py
ds1052/examples/screenshot.py
ds1052/tests/__init__.py
ds1052/tests/test_ds1052.py
ds1052/tests/test_tmc.py
ya_ds1052.egg-info/PKG-INFO
ya_ds1052.egg-info/SOURCES.txt
ya_ds1052.egg-info/dependency_links.txt
ya_ds1052.egg-info/requires.txt
ya_ds1052.egg-info/top_level.txt