Metadata-Version: 2.1
Name: ya-ds1052
Version: 0.1.2
Summary: Remote control of Rigol DS1000E/D oscilloscopes
Home-page: https://gitlab.com/adeuring/ya_ds1052
Author: Abel Deuring
Author-email: adeuring@gmx.net
License: GPL3
Platform: UNKNOWN
Classifier: Development Status :: 3 - Alpha
Classifier: License :: OSI Approved :: GNU General Public License v3 or later (GPLv3+)
Classifier: Topic :: System :: Hardware :: Hardware Drivers
